pyglmnet/__init__.py
pyglmnet/base.py
pyglmnet/benchmarks.py
pyglmnet/datasets.py
pyglmnet/metrics.py
pyglmnet/pyglmnet.py
pyglmnet/utils.py
pyglmnet-1.1.dist-info/LICENSE
pyglmnet-1.1.dist-info/METADATA
pyglmnet-1.1.dist-info/WHEEL
pyglmnet-1.1.dist-info/top_level.txt
pyglmnet-1.1.dist-info/RECORD
