Metadata-Version: 2.1
Name: pyglmnet
Version: 1.1
Summary: Elastic-net regularized generalized linear models.
Home-page: http://glm-tools.github.io/pyglmnet/
Maintainer: Pavan Ramkumar
Maintainer-email: pavan.ramkumar@gmail.com
License: MIT
Download-URL: https://github.com/glm-tools/pyglmnet.git
Project-URL: Documentation, http://glm-tools.github.io/pyglmnet/
Project-URL: Bug Reports, https://github.com/glm-tools/pyglmnet/issues
Project-URL: Source, https://github.com/glm-tools/pyglmnet
Platform: any
Classifier: Intended Audience :: Science/Research
Classifier: Intended Audience :: Developers
Classifier: License :: OSI Approved
Classifier: Programming Language :: Python
Classifier: Topic :: Software Development
Classifier: Topic :: Scientific/Engineering
Classifier: Operating System :: Microsoft :: Windows
Classifier: Operating System :: POSIX
Classifier: Operating System :: Unix
Classifier: Operating System :: MacOS
Classifier: Programming Language :: Python :: 2
Classifier: Programming Language :: Python :: 2.7
Classifier: Programming Language :: Python :: 3
Classifier: Programming Language :: Python :: 3.5
Classifier: Programming Language :: Python :: 3.6
Classifier: Programming Language :: Python :: 3.7
